main.py
git2pdf/DejaVuSans.ttf
git2pdf/main.py
git2pdf-0.1.7.dist-info/LICENSE.txt
git2pdf-0.1.7.dist-info/METADATA
git2pdf-0.1.7.dist-info/WHEEL
git2pdf-0.1.7.dist-info/entry_points.txt
git2pdf-0.1.7.dist-info/top_level.txt
git2pdf-0.1.7.dist-info/RECORD
